cosmospy_protobuf/__init__.py
cosmospy_protobuf/__init__.pyi
cosmospy_protobuf/proofs.proto
cosmospy_protobuf/proofs_pb2.py
cosmospy_protobuf/proofs_pb2.pyi
cosmospy_protobuf/cosmos/__init__.py
cosmospy_protobuf/cosmos/__init__.pyi
cosmospy_protobuf/cosmos/auth/__init__.py
cosmospy_protobuf/cosmos/auth/__init__.pyi
cosmospy_protobuf/cosmos/auth/v1beta1/__init__.py
cosmospy_protobuf/cosmos/auth/v1beta1/__init__.pyi
cosmospy_protobuf/cosmos/auth/v1beta1/auth.proto
cosmospy_protobuf/cosmos/auth/v1beta1/auth_pb2.py
cosmospy_protobuf/cosmos/auth/v1beta1/auth_pb2.pyi
cosmospy_protobuf/cosmos/auth/v1beta1/genesis.proto
cosmospy_protobuf/cosmos/auth/v1beta1/genesis_pb2.py
cosmospy_protobuf/cosmos/auth/v1beta1/genesis_pb2.pyi
cosmospy_protobuf/cosmos/auth/v1beta1/query.proto
cosmospy_protobuf/cosmos/auth/v1beta1/query_grpc.py
cosmospy_protobuf/cosmos/auth/v1beta1/query_pb2.py
cosmospy_protobuf/cosmos/auth/v1beta1/query_pb2.pyi
cosmospy_protobuf/cosmos/auth/v1beta1/query_pb2_grpc.py
cosmospy_protobuf/cosmos/authz/__init__.py
cosmospy_protobuf/cosmos/authz/__init__.pyi
cosmospy_protobuf/cosmos/authz/v1beta1/__init__.py
cosmospy_protobuf/cosmos/authz/v1beta1/__init__.pyi
cosmospy_protobuf/cosmos/authz/v1beta1/authz.proto
cosmospy_protobuf/cosmos/authz/v1beta1/authz_pb2.py
cosmospy_protobuf/cosmos/authz/v1beta1/authz_pb2.pyi
cosmospy_protobuf/cosmos/authz/v1beta1/event.proto
cosmospy_protobuf/cosmos/authz/v1beta1/event_pb2.py
cosmospy_protobuf/cosmos/authz/v1beta1/event_pb2.pyi
cosmospy_protobuf/cosmos/authz/v1beta1/genesis.proto
cosmospy_protobuf/cosmos/authz/v1beta1/genesis_pb2.py
cosmospy_protobuf/cosmos/authz/v1beta1/genesis_pb2.pyi
cosmospy_protobuf/cosmos/authz/v1beta1/query.proto
cosmospy_protobuf/cosmos/authz/v1beta1/query_grpc.py
cosmospy_protobuf/cosmos/authz/v1beta1/query_pb2.py
cosmospy_protobuf/cosmos/authz/v1beta1/query_pb2.pyi
cosmospy_protobuf/cosmos/authz/v1beta1/query_pb2_grpc.py
cosmospy_protobuf/cosmos/authz/v1beta1/tx.proto
cosmospy_protobuf-0.3.0.dist-info/METADATA
cosmospy_protobuf-0.3.0.dist-info/WHEEL
cosmospy_protobuf-0.3.0.dist-info/RECORD
