Metadata-Version: 2.1
Name: cosmospy_protobuf
Version: 0.3.0
Summary: This package contains a compiled python version of all cosmos protobuf files with their dependencies
Project-URL: Homepage, https://github.com/ctrl-Felix/cosmospy-protobuf/
Project-URL: Bug Tracker, https://github.com/ctrl-Felix/cosmospy-protobuf/issues
Author-email: ctrl-felix <dev@ctrl-felix.de>
License: BSD 3-Clause License
Keywords: cosmos,cosmos-protobuf,cosmospy,cosmospy-protobuf,proto,protobuf
Classifier: Operating System :: OS Independent
Classifier: Programming Language :: Python :: 3
Requires-Dist: protobuf
